pyGuardPoint/CustomWebsocketTransport.py
pyGuardPoint/CustomWebsocketTransportOld.py
pyGuardPoint/__init__.py
pyGuardPoint/_guardpoint_accessgroups.py
pyGuardPoint/_guardpoint_alarmstates.py
pyGuardPoint/_guardpoint_alarmzones.py
pyGuardPoint/_guardpoint_areas.py
pyGuardPoint/_guardpoint_cardholders.py
pyGuardPoint/_guardpoint_cardholdertypes.py
pyGuardPoint/_guardpoint_cards.py
pyGuardPoint/_guardpoint_controllers.py
pyGuardPoint/_guardpoint_customizedfields.py
pyGuardPoint/_guardpoint_departments.py
pyGuardPoint/_guardpoint_diagnostic.py
pyGuardPoint/_guardpoint_events.py
pyGuardPoint/_guardpoint_genericinformation.py
pyGuardPoint/_guardpoint_inputs.py
pyGuardPoint/_guardpoint_ouputs.py
pyGuardPoint/_guardpoint_personaldetails.py
pyGuardPoint/_guardpoint_readers.py
pyGuardPoint/_guardpoint_scheduledmags.py
pyGuardPoint/_guardpoint_securitygroups.py
pyGuardPoint/_guardpoint_sites.py
pyGuardPoint/_odata_filter.py
pyGuardPoint/_str_match_algo.py
pyGuardPoint/guardpoint.py
pyGuardPoint/guardpoint_asyncio.py
pyGuardPoint/guardpoint_connection.py
pyGuardPoint/guardpoint_dataclasses.py
pyGuardPoint/guardpoint_error.py
pyGuardPoint/guardpoint_threaded.py
pyGuardPoint/guardpoint_utils.py
pyGuardPoint/gp_asyncio/__init__.py
pyGuardPoint/gp_asyncio/_async_guardpoint_accessgroups.py
pyGuardPoint/gp_asyncio/_async_guardpoint_alarmstates.py
pyGuardPoint/gp_asyncio/_async_guardpoint_alarmzones.py
pyGuardPoint/gp_asyncio/_async_guardpoint_areas.py
pyGuardPoint/gp_asyncio/_async_guardpoint_cardholders.py
pyGuardPoint/gp_asyncio/_async_guardpoint_cardholdertypes.py
pyGuardPoint/gp_asyncio/_async_guardpoint_cards.py
pyGuardPoint/gp_asyncio/_async_guardpoint_controllers.py
pyGuardPoint/gp_asyncio/_async_guardpoint_customizedfields.py
pyGuardPoint/gp_asyncio/_async_guardpoint_departments.py
pyGuardPoint/gp_asyncio/_async_guardpoint_diagnostic.py
pyGuardPoint/gp_asyncio/_async_guardpoint_events.py
pyGuardPoint/gp_asyncio/_async_guardpoint_genericinformation.py
pyguardpoint-1.9.4.dist-info/licenses/LICENSE.txt
pyguardpoint-1.9.4.dist-info/METADATA
pyguardpoint-1.9.4.dist-info/WHEEL
pyguardpoint-1.9.4.dist-info/top_level.txt
pyguardpoint-1.9.4.dist-info/RECORD
