Metadata-Version: 2.4
Name: pyGuardPoint
Version: 1.9.4
Summary: Python wrapper for GuardPoint 10 Access Control System
Author: John Owen
Maintainer-email: sales@sensoraccess.co.uk
Requires-Python: >3.9.0
License-File: LICENSE.txt
Requires-Dist: validators
Requires-Dist: fuzzywuzzy
Requires-Dist: cryptography
Requires-Dist: pysignalr>=1.3.0
Requires-Dist: websockets
Requires-Dist: python-Levenshtein
Dynamic: author
Dynamic: description
Dynamic: description-content-type
Dynamic: license-file
Dynamic: maintainer-email
Dynamic: requires-dist
Dynamic: requires-python
Dynamic: summary
